README.rst
setup.py
nwid/__init__.py
nwid/display.py
nwid/events.py
nwid.egg-info/PKG-INFO
nwid.egg-info/SOURCES.txt
nwid.egg-info/dependency_links.txt
nwid.egg-info/top_level.txt