Metadata-Version: 1.1
Name: nwid
Version: 0.1
Summary: A terminal widget framework for humans.
Home-page: https://github.com/hbradleyiii/nwid
Author: Harold Bradley III
Author-email: harold@bradleystudio.net
License: MIT License
Download-URL: https://github.com/hbradleyiii/nwid/archive/v0.1-planning.tar.gz
Keywords: server development,terminal programming,terminal,terminal widgets
Platform: UNKNOWN
Classifier: Development Status :: 1 - Planning
Classifier: Intended Audience :: Developers
Classifier: Topic :: Software Development :: Build Tools
Classifier: License :: OSI Approved :: MIT License
Classifier: Programming Language :: Python :: 2
Classifier: Programming Language :: Python :: 2.6
Classifier: Programming Language :: Python :: 2.7
Classifier: Programming Language :: Python :: 3
Classifier: Programming Language :: Python :: 3.2
Classifier: Programming Language :: Python :: 3.3
Classifier: Programming Language :: Python :: 3.4
Classifier: Programming Language :: Python :: 3.5
